{
  "appId": "com.keymuse",
  "latestVersionCode": 37,
  "latestVersionName": "0.1.37",
  "apkUrl": "https://github.com/liquidlightIce/KeyMuse-updates/releases/download/v0.1.37/KeyMuse-v0.1.37-debug.apk",
  "apkSha256": "ad4db2235b74f6355a75a55507b6cfcec8071c2285c5691ccdee07af688f2d2a",
  "releaseNotes": [
    "El pad Play del Arturia MiniLab 3 ahora inicia, pausa y reanuda la leccion.",
    "Al terminar una leccion, el pad Play la reinicia y comienza nuevamente.",
    "Mientras Practice espera una correccion, el pad no salta la nota pendiente.",
    "Los mensajes del pad se aislan del teclado, la puntuacion y el cambio de octava."
  ],
  "mandatory": false
}
