{
    "appId":  "com.keymuse",
    "latestVersionCode":  45,
    "latestVersionName":  "0.1.45",
    "apkUrl":  "https://github.com/liquidlightIce/KeyMuse-updates/releases/download/v0.1.45/KeyMuse-v0.1.45-release.apk",
    "apkSha256":  "d2032940dde631fe4949ceb79e3d29f9a2e936fb9b47a59e651fdb5bde059825",
    "mandatory":  false,
    "releaseNotes":  [
                         "Adds immersive fullscreen mode to give the piano roll more vertical space.",
                         "Adds a compact in-app status cluster for time, battery, and Online/Offline state.",
                         "Collapses the lesson selector by default so changing songs no longer consumes practice space."
                     ]
}